bitme
