Metadata-Version: 1.1
Name: bitme
Version: 0.0.7
Summary: Bitme bitcoin exchange API
Home-page: https://github.com/hank/bitme-python
Author: Erik Gregg
Author-email: ralree@gmail.com
License: LICENSE
Keywords: bitme bitcoin exchange api trade
Platform: UNKNOWN
Classifier: Development Status :: 2 - Pre-Alpha
Classifier: License :: OSI Approved :: MIT License
